<?xml version='1.0' encoding='us-ascii'?>
<annotation>
	<folder>hat01</folder>
	<filename>000090.jpg</filename>
	<path>D:\dataset\hat01\000090.jpg</path>
	<source>
		<database>Unknown</database>
	</source>
	<size>
		<width>500</width>
		<height>653</height>
		<depth>3</depth>
	</size>
	<segmented>0</segmented>
	<object>
		<name>hat</name>
		<pose>Unspecified</pose>
		<truncated>0</truncated>
		<difficult>0</difficult>
		<bndbox>
			<xmin>138</xmin>
			<ymin>19</ymin>
			<xmax>185</xmax>
			<ymax>68</ymax>
		</bndbox>
	</object>
	<object>
		<name>hat</name>
		<pose>Unspecified</pose>
		<truncated>0</truncated>
		<difficult>0</difficult>
		<bndbox>
			<xmin>187</xmin>
			<ymin>52</ymin>
			<xmax>210</xmax>
			<ymax>81</ymax>
		</bndbox>
	</object>
	<object>
		<name>hat</name>
		<pose>Unspecified</pose>
		<truncated>0</truncated>
		<difficult>0</difficult>
		<bndbox>
			<xmin>197</xmin>
			<ymin>115</ymin>
			<xmax>291</xmax>
			<ymax>216</ymax>
		</bndbox>
	</object>
	<object>
		<name>hat</name>
		<pose>Unspecified</pose>
		<truncated>0</truncated>
		<difficult>0</difficult>
		<bndbox>
			<xmin>346</xmin>
			<ymin>41</ymin>
			<xmax>384</xmax>
			<ymax>81</ymax>
		</bndbox>
	</object>
	<object>
		<name>hat</name>
		<pose>Unspecified</pose>
		<truncated>0</truncated>
		<difficult>1</difficult>
		<bndbox>
			<xmin>215</xmin>
			<ymin>73</ymin>
			<xmax>226</xmax>
			<ymax>84</ymax>
		</bndbox>
	</object>
	<object>
		<name>hat</name>
		<pose>Unspecified</pose>
		<truncated>0</truncated>
		<difficult>1</difficult>
		<bndbox>
			<xmin>233</xmin>
			<ymin>82</ymin>
			<xmax>243</xmax>
			<ymax>95</ymax>
		</bndbox>
	</object>
	<object>
		<name>hat</name>
		<pose>Unspecified</pose>
		<truncated>0</truncated>
		<difficult>1</difficult>
		<bndbox>
			<xmin>281</xmin>
			<ymin>84</ymin>
			<xmax>290</xmax>
			<ymax>94</ymax>
		</bndbox>
	</object>
	<object>
		<name>hat</name>
		<pose>Unspecified</pose>
		<truncated>0</truncated>
		<difficult>1</difficult>
		<bndbox>
			<xmin>301</xmin>
			<ymin>83</ymin>
			<xmax>311</xmax>
			<ymax>92</ymax>
		</bndbox>
	</object>
	<object>
		<name>hat</name>
		<pose>Unspecified</pose>
		<truncated>0</truncated>
		<difficult>1</difficult>
		<bndbox>
			<xmin>314</xmin>
			<ymin>98</ymin>
			<xmax>326</xmax>
			<ymax>109</ymax>
		</bndbox>
	</object>
	<object>
		<name>hat</name>
		<pose>Unspecified</pose>
		<truncated>0</truncated>
		<difficult>1</difficult>
		<bndbox>
			<xmin>265</xmin>
			<ymin>86</ymin>
			<xmax>274</xmax>
			<ymax>96</ymax>
		</bndbox>
	</object>
	<object>
		<name>hat</name>
		<pose>Unspecified</pose>
		<truncated>0</truncated>
		<difficult>1</difficult>
		<bndbox>
			<xmin>253</xmin>
			<ymin>87</ymin>
			<xmax>262</xmax>
			<ymax>98</ymax>
		</bndbox>
	</object>
</annotation>