<?xml version='1.0' encoding='us-ascii'?>
<annotation>
	<folder>hat01</folder>
	<filename>000085.jpg</filename>
	<path>D:\dataset\hat01\000085.jpg</path>
	<source>
		<database>Unknown</database>
	</source>
	<size>
		<width>583</width>
		<height>408</height>
		<depth>3</depth>
	</size>
	<segmented>0</segmented>
	<object>
		<name>hat</name>
		<pose>Unspecified</pose>
		<truncated>1</truncated>
		<difficult>0</difficult>
		<bndbox>
			<xmin>59</xmin>
			<ymin>1</ymin>
			<xmax>476</xmax>
			<ymax>406</ymax>
		</bndbox>
	</object>
</annotation>