<?xml version='1.0' encoding='us-ascii'?>
<annotation>
	<folder>JPEGImages</folder>
	<filename>000101.jpg</filename>
	<path>D:\study\project\label_hat\VOCdevkit\VOC2024\JPEGImages\000101.jpg</path>
	<source>
		<database>Unknown</database>
	</source>
	<size>
		<width>700</width>
		<height>466</height>
		<depth>3</depth>
	</size>
	<segmented>0</segmented>
	<object>
		<name>hat</name>
		<pose>Unspecified</pose>
		<truncated>1</truncated>
		<difficult>0</difficult>
		<bndbox>
			<xmin>389</xmin>
			<ymin>6</ymin>
			<xmax>700</xmax>
			<ymax>336</ymax>
		</bndbox>
	</object>
	<object>
		<name>person</name>
		<pose>Unspecified</pose>
		<truncated>0</truncated>
		<difficult>0</difficult>
		<bndbox>
			<xmin>201</xmin>
			<ymin>108</ymin>
			<xmax>306</xmax>
			<ymax>207</ymax>
		</bndbox>
	</object>
	<object>
		<name>person</name>
		<pose>Unspecified</pose>
		<truncated>0</truncated>
		<difficult>0</difficult>
		<bndbox>
			<xmin>114</xmin>
			<ymin>81</ymin>
			<xmax>187</xmax>
			<ymax>174</ymax>
		</bndbox>
	</object>
	<object>
		<name>person</name>
		<pose>Unspecified</pose>
		<truncated>0</truncated>
		<difficult>0</difficult>
		<bndbox>
			<xmin>351</xmin>
			<ymin>78</ymin>
			<xmax>433</xmax>
			<ymax>197</ymax>
		</bndbox>
	</object>
</annotation>