<?xml version='1.0' encoding='us-ascii'?>
<annotation>
	<folder>JPEGImages</folder>
	<filename>000298.jpg</filename>
	<path>D:\study\project\label_hat\VOCdevkit\VOC2024\JPEGImages\000298.jpg</path>
	<source>
		<database>Unknown</database>
	</source>
	<size>
		<width>680</width>
		<height>510</height>
		<depth>3</depth>
	</size>
	<segmented>0</segmented>
	<object>
		<name>hat</name>
		<pose>Unspecified</pose>
		<truncated>0</truncated>
		<difficult>0</difficult>
		<bndbox>
			<xmin>89</xmin>
			<ymin>194</ymin>
			<xmax>115</xmax>
			<ymax>222</ymax>
		</bndbox>
	</object>
	<object>
		<name>hat</name>
		<pose>Unspecified</pose>
		<truncated>0</truncated>
		<difficult>0</difficult>
		<bndbox>
			<xmin>143</xmin>
			<ymin>166</ymin>
			<xmax>174</xmax>
			<ymax>203</ymax>
		</bndbox>
	</object>
	<object>
		<name>hat</name>
		<pose>Unspecified</pose>
		<truncated>0</truncated>
		<difficult>0</difficult>
		<bndbox>
			<xmin>251</xmin>
			<ymin>169</ymin>
			<xmax>276</xmax>
			<ymax>201</ymax>
		</bndbox>
	</object>
	<object>
		<name>hat</name>
		<pose>Unspecified</pose>
		<truncated>0</truncated>
		<difficult>1</difficult>
		<bndbox>
			<xmin>240</xmin>
			<ymin>178</ymin>
			<xmax>256</xmax>
			<ymax>201</ymax>
		</bndbox>
	</object>
	<object>
		<name>person</name>
		<pose>Unspecified</pose>
		<truncated>0</truncated>
		<difficult>0</difficult>
		<bndbox>
			<xmin>137</xmin>
			<ymin>183</ymin>
			<xmax>153</xmax>
			<ymax>208</ymax>
		</bndbox>
	</object>
</annotation>