<?xml version='1.0' encoding='us-ascii'?>
<annotation>
	<folder>JPEGImages</folder>
	<filename>000481.jpg</filename>
	<path>D:\study\project\label_hat\VOCdevkit\VOC2024\JPEGImages\000481.jpg</path>
	<source>
		<database>Unknown</database>
	</source>
	<size>
		<width>505</width>
		<height>669</height>
		<depth>3</depth>
	</size>
	<segmented>0</segmented>
	<object>
		<name>hat</name>
		<pose>Unspecified</pose>
		<truncated>0</truncated>
		<difficult>0</difficult>
		<bndbox>
			<xmin>104</xmin>
			<ymin>107</ymin>
			<xmax>194</xmax>
			<ymax>222</ymax>
		</bndbox>
	</object>
	<object>
		<name>person</name>
		<pose>Unspecified</pose>
		<truncated>0</truncated>
		<difficult>0</difficult>
		<bndbox>
			<xmin>214</xmin>
			<ymin>102</ymin>
			<xmax>231</xmax>
			<ymax>123</ymax>
		</bndbox>
	</object>
	<object>
		<name>person</name>
		<pose>Unspecified</pose>
		<truncated>0</truncated>
		<difficult>0</difficult>
		<bndbox>
			<xmin>190</xmin>
			<ymin>106</ymin>
			<xmax>205</xmax>
			<ymax>125</ymax>
		</bndbox>
	</object>
</annotation>