<?xml version='1.0' encoding='us-ascii'?>
<annotation verified="yes">
	<folder>Img_2000</folder>
	<filename>PartB_00420.jpg</filename>
	<path>C:\Users\Administrator\Desktop\dataset_2.0\Img_2000\Img_1290.jpeg</path>
	<source>
		<database>Unknown</database>
	</source>
	<size>
		<width>1600</width>
		<height>1067</height>
		<depth>3</depth>
	</size>
	<segmented>0</segmented>
	<object>
		<name>person</name>
		<pose>Unspecified</pose>
		<truncated>0</truncated>
		<difficult>0</difficult>
		<bndbox>
			<xmin>12</xmin>
			<ymin>539</ymin>
			<xmax>140</xmax>
			<ymax>684</ymax>
		</bndbox>
	</object>
	<object>
		<name>person</name>
		<pose>Unspecified</pose>
		<truncated>0</truncated>
		<difficult>0</difficult>
		<bndbox>
			<xmin>183</xmin>
			<ymin>526</ymin>
			<xmax>257</xmax>
			<ymax>606</ymax>
		</bndbox>
	</object>
	<object>
		<name>person</name>
		<pose>Unspecified</pose>
		<truncated>0</truncated>
		<difficult>0</difficult>
		<bndbox>
			<xmin>335</xmin>
			<ymin>525</ymin>
			<xmax>413</xmax>
			<ymax>596</ymax>
		</bndbox>
	</object>
	<object>
		<name>person</name>
		<pose>Unspecified</pose>
		<truncated>0</truncated>
		<difficult>0</difficult>
		<bndbox>
			<xmin>499</xmin>
			<ymin>511</ymin>
			<xmax>567</xmax>
			<ymax>573</ymax>
		</bndbox>
	</object>
	<object>
		<name>person</name>
		<pose>Unspecified</pose>
		<truncated>0</truncated>
		<difficult>0</difficult>
		<bndbox>
			<xmin>628</xmin>
			<ymin>516</ymin>
			<xmax>688</xmax>
			<ymax>572</ymax>
		</bndbox>
	</object>
	<object>
		<name>person</name>
		<pose>Unspecified</pose>
		<truncated>0</truncated>
		<difficult>0</difficult>
		<bndbox>
			<xmin>659</xmin>
			<ymin>660</ymin>
			<xmax>838</xmax>
			<ymax>857</ymax>
		</bndbox>
	</object>
	<object>
		<name>person</name>
		<pose>Unspecified</pose>
		<truncated>0</truncated>
		<difficult>0</difficult>
		<bndbox>
			<xmin>1155</xmin>
			<ymin>573</ymin>
			<xmax>1268</xmax>
			<ymax>685</ymax>
		</bndbox>
	</object>
	<object>
		<name>person</name>
		<pose>Unspecified</pose>
		<truncated>0</truncated>
		<difficult>0</difficult>
		<bndbox>
			<xmin>1243</xmin>
			<ymin>556</ymin>
			<xmax>1334</xmax>
			<ymax>650</ymax>
		</bndbox>
	</object>
	<object>
		<name>person</name>
		<pose>Unspecified</pose>
		<truncated>0</truncated>
		<difficult>0</difficult>
		<bndbox>
			<xmin>1387</xmin>
			<ymin>478</ymin>
			<xmax>1445</xmax>
			<ymax>531</ymax>
		</bndbox>
	</object>
</annotation>