<?xml version='1.0' encoding='us-ascii'?>
<annotation>
	<folder>Img_2000</folder>
	<filename>PartB_00651.jpg</filename>
	<path>C:\Users\Administrator\Desktop\dataset_2.0\Img_2000\Img_1500.jpeg</path>
	<source>
		<database>Unknown</database>
	</source>
	<size>
		<width>1630</width>
		<height>955</height>
		<depth>3</depth>
	</size>
	<segmented>0</segmented>
	<object>
		<name>person</name>
		<pose>Unspecified</pose>
		<truncated>0</truncated>
		<difficult>0</difficult>
		<bndbox>
			<xmin>121</xmin>
			<ymin>379</ymin>
			<xmax>157</xmax>
			<ymax>423</ymax>
		</bndbox>
	</object>
	<object>
		<name>person</name>
		<pose>Unspecified</pose>
		<truncated>0</truncated>
		<difficult>0</difficult>
		<bndbox>
			<xmin>79</xmin>
			<ymin>357</ymin>
			<xmax>110</xmax>
			<ymax>402</ymax>
		</bndbox>
	</object>
	<object>
		<name>person</name>
		<pose>Unspecified</pose>
		<truncated>0</truncated>
		<difficult>0</difficult>
		<bndbox>
			<xmin>195</xmin>
			<ymin>422</ymin>
			<xmax>231</xmax>
			<ymax>468</ymax>
		</bndbox>
	</object>
	<object>
		<name>person</name>
		<pose>Unspecified</pose>
		<truncated>0</truncated>
		<difficult>0</difficult>
		<bndbox>
			<xmin>243</xmin>
			<ymin>392</ymin>
			<xmax>279</xmax>
			<ymax>442</ymax>
		</bndbox>
	</object>
	<object>
		<name>person</name>
		<pose>Unspecified</pose>
		<truncated>0</truncated>
		<difficult>0</difficult>
		<bndbox>
			<xmin>339</xmin>
			<ymin>424</ymin>
			<xmax>384</xmax>
			<ymax>470</ymax>
		</bndbox>
	</object>
	<object>
		<name>person</name>
		<pose>Unspecified</pose>
		<truncated>0</truncated>
		<difficult>0</difficult>
		<bndbox>
			<xmin>365</xmin>
			<ymin>361</ymin>
			<xmax>401</xmax>
			<ymax>400</ymax>
		</bndbox>
	</object>
	<object>
		<name>person</name>
		<pose>Unspecified</pose>
		<truncated>0</truncated>
		<difficult>0</difficult>
		<bndbox>
			<xmin>478</xmin>
			<ymin>450</ymin>
			<xmax>522</xmax>
			<ymax>501</ymax>
		</bndbox>
	</object>
	<object>
		<name>person</name>
		<pose>Unspecified</pose>
		<truncated>0</truncated>
		<difficult>0</difficult>
		<bndbox>
			<xmin>476</xmin>
			<ymin>397</ymin>
			<xmax>511</xmax>
			<ymax>438</ymax>
		</bndbox>
	</object>
	<object>
		<name>person</name>
		<pose>Unspecified</pose>
		<truncated>0</truncated>
		<difficult>0</difficult>
		<bndbox>
			<xmin>584</xmin>
			<ymin>459</ymin>
			<xmax>625</xmax>
			<ymax>511</ymax>
		</bndbox>
	</object>
	<object>
		<name>person</name>
		<pose>Unspecified</pose>
		<truncated>0</truncated>
		<difficult>0</difficult>
		<bndbox>
			<xmin>613</xmin>
			<ymin>478</ymin>
			<xmax>660</xmax>
			<ymax>541</ymax>
		</bndbox>
	</object>
	<object>
		<name>person</name>
		<pose>Unspecified</pose>
		<truncated>0</truncated>
		<difficult>0</difficult>
		<bndbox>
			<xmin>716</xmin>
			<ymin>474</ymin>
			<xmax>747</xmax>
			<ymax>512</ymax>
		</bndbox>
	</object>
	<object>
		<name>person</name>
		<pose>Unspecified</pose>
		<truncated>0</truncated>
		<difficult>0</difficult>
		<bndbox>
			<xmin>736</xmin>
			<ymin>500</ymin>
			<xmax>785</xmax>
			<ymax>564</ymax>
		</bndbox>
	</object>
	<object>
		<name>person</name>
		<pose>Unspecified</pose>
		<truncated>0</truncated>
		<difficult>0</difficult>
		<bndbox>
			<xmin>847</xmin>
			<ymin>491</ymin>
			<xmax>884</xmax>
			<ymax>540</ymax>
		</bndbox>
	</object>
	<object>
		<name>person</name>
		<pose>Unspecified</pose>
		<truncated>0</truncated>
		<difficult>0</difficult>
		<bndbox>
			<xmin>963</xmin>
			<ymin>510</ymin>
			<xmax>1002</xmax>
			<ymax>563</ymax>
		</bndbox>
	</object>
	<object>
		<name>person</name>
		<pose>Unspecified</pose>
		<truncated>0</truncated>
		<difficult>0</difficult>
		<bndbox>
			<xmin>1118</xmin>
			<ymin>554</ymin>
			<xmax>1186</xmax>
			<ymax>632</ymax>
		</bndbox>
	</object>
	<object>
		<name>person</name>
		<pose>Unspecified</pose>
		<truncated>0</truncated>
		<difficult>0</difficult>
		<bndbox>
			<xmin>1161</xmin>
			<ymin>243</ymin>
			<xmax>1464</xmax>
			<ymax>564</ymax>
		</bndbox>
	</object>
</annotation>