<?xml version='1.0' encoding='us-ascii'?>
<annotation>
	<folder>250-499</folder>
	<filename>PartA_00317.jpg</filename>
	<path>/home/pengdezhi/&#25968;&#25454;&#26631;&#27880;/250-499/317.jpg</path>
	<source>
		<database>Unknown</database>
	</source>
	<size>
		<width>833</width>
		<height>464</height>
		<depth>3</depth>
	</size>
	<segmented>0</segmented>
	<object>
    <name>person</name>
		<pose>Unspecified</pose>
		<truncated>0</truncated>
		<difficult>0</difficult>
		<bndbox>
			<xmin>170</xmin>
			<ymin>162</ymin>
			<xmax>214</xmax>
			<ymax>205</ymax>
		</bndbox>
	</object>
	<object>
    <name>person</name>
		<pose>Unspecified</pose>
		<truncated>0</truncated>
		<difficult>0</difficult>
		<bndbox>
			<xmin>295</xmin>
			<ymin>83</ymin>
			<xmax>317</xmax>
			<ymax>109</ymax>
		</bndbox>
	</object>
	<object>
    <name>person</name>
		<pose>Unspecified</pose>
		<truncated>0</truncated>
		<difficult>0</difficult>
		<bndbox>
			<xmin>439</xmin>
			<ymin>81</ymin>
			<xmax>454</xmax>
			<ymax>100</ymax>
		</bndbox>
	</object>
	<object>
    <name>person</name>
		<pose>Unspecified</pose>
		<truncated>0</truncated>
		<difficult>0</difficult>
		<bndbox>
			<xmin>509</xmin>
			<ymin>94</ymin>
			<xmax>528</xmax>
			<ymax>114</ymax>
		</bndbox>
	</object>
	<object>
    <name>person</name>
		<pose>Unspecified</pose>
		<truncated>0</truncated>
		<difficult>0</difficult>
		<bndbox>
			<xmin>548</xmin>
			<ymin>85</ymin>
			<xmax>563</xmax>
			<ymax>101</ymax>
		</bndbox>
	</object>
	<object>
    <name>person</name>
		<pose>Unspecified</pose>
		<truncated>0</truncated>
		<difficult>0</difficult>
		<bndbox>
			<xmin>579</xmin>
			<ymin>87</ymin>
			<xmax>595</xmax>
			<ymax>105</ymax>
		</bndbox>
	</object>
	<object>
    <name>person</name>
		<pose>Unspecified</pose>
		<truncated>0</truncated>
		<difficult>0</difficult>
		<bndbox>
			<xmin>612</xmin>
			<ymin>92</ymin>
			<xmax>629</xmax>
			<ymax>110</ymax>
		</bndbox>
	</object>
	<object>
    <name>person</name>
		<pose>Unspecified</pose>
		<truncated>0</truncated>
		<difficult>0</difficult>
		<bndbox>
			<xmin>542</xmin>
			<ymin>105</ymin>
			<xmax>561</xmax>
			<ymax>130</ymax>
		</bndbox>
	</object>
	<object>
    <name>person</name>
		<pose>Unspecified</pose>
		<truncated>0</truncated>
		<difficult>0</difficult>
		<bndbox>
			<xmin>553</xmin>
			<ymin>98</ymin>
			<xmax>569</xmax>
			<ymax>118</ymax>
		</bndbox>
	</object>
	<object>
    <name>person</name>
		<pose>Unspecified</pose>
		<truncated>0</truncated>
		<difficult>0</difficult>
		<bndbox>
			<xmin>616</xmin>
			<ymin>120</ymin>
			<xmax>635</xmax>
			<ymax>142</ymax>
		</bndbox>
	</object>
	<object>
    <name>person</name>
		<pose>Unspecified</pose>
		<truncated>0</truncated>
		<difficult>0</difficult>
		<bndbox>
			<xmin>624</xmin>
			<ymin>115</ymin>
			<xmax>641</xmax>
			<ymax>134</ymax>
		</bndbox>
	</object>
	<object>
    <name>person</name>
		<pose>Unspecified</pose>
		<truncated>0</truncated>
		<difficult>0</difficult>
		<bndbox>
			<xmin>613</xmin>
			<ymin>151</ymin>
			<xmax>638</xmax>
			<ymax>188</ymax>
		</bndbox>
	</object>
	<object>
    <name>person</name>
		<pose>Unspecified</pose>
		<truncated>0</truncated>
		<difficult>0</difficult>
		<bndbox>
			<xmin>677</xmin>
			<ymin>111</ymin>
			<xmax>695</xmax>
			<ymax>136</ymax>
		</bndbox>
	</object>
	<object>
    <name>person</name>
		<pose>Unspecified</pose>
		<truncated>0</truncated>
		<difficult>0</difficult>
		<bndbox>
			<xmin>663</xmin>
			<ymin>171</ymin>
			<xmax>688</xmax>
			<ymax>207</ymax>
		</bndbox>
	</object>
	<object>
    <name>person</name>
		<pose>Unspecified</pose>
		<truncated>0</truncated>
		<difficult>0</difficult>
		<bndbox>
			<xmin>743</xmin>
			<ymin>168</ymin>
			<xmax>770</xmax>
			<ymax>201</ymax>
		</bndbox>
	</object>
</annotation>