<?xml version='1.0' encoding='us-ascii'?>
<annotation>
	<folder>750-999</folder>
	<filename>PartA_00919.jpg</filename>
	<path>/media/zrcai/study/lab/0818data/750-999/750-999/919.jpg</path>
	<source>
		<database>Unknown</database>
	</source>
	<size>
		<width>1047</width>
		<height>606</height>
		<depth>3</depth>
	</size>
	<segmented>0</segmented>
	<object>
    <name>person</name>
		<pose>Unspecified</pose>
		<truncated>0</truncated>
		<difficult>0</difficult>
		<bndbox>
			<xmin>467</xmin>
			<ymin>125</ymin>
			<xmax>494</xmax>
			<ymax>157</ymax>
		</bndbox>
	</object>
	<object>
    <name>person</name>
		<pose>Unspecified</pose>
		<truncated>0</truncated>
		<difficult>0</difficult>
		<bndbox>
			<xmin>506</xmin>
			<ymin>170</ymin>
			<xmax>530</xmax>
			<ymax>201</ymax>
		</bndbox>
	</object>
	<object>
    <name>person</name>
		<pose>Unspecified</pose>
		<truncated>0</truncated>
		<difficult>0</difficult>
		<bndbox>
			<xmin>565</xmin>
			<ymin>178</ymin>
			<xmax>597</xmax>
			<ymax>212</ymax>
		</bndbox>
	</object>
	<object>
    <name>person</name>
		<pose>Unspecified</pose>
		<truncated>0</truncated>
		<difficult>0</difficult>
		<bndbox>
			<xmin>629</xmin>
			<ymin>193</ymin>
			<xmax>664</xmax>
			<ymax>229</ymax>
		</bndbox>
	</object>
	<object>
    <name>person</name>
		<pose>Unspecified</pose>
		<truncated>0</truncated>
		<difficult>0</difficult>
		<bndbox>
			<xmin>593</xmin>
			<ymin>77</ymin>
			<xmax>609</xmax>
			<ymax>91</ymax>
		</bndbox>
	</object>
	<object>
    <name>person</name>
		<pose>Unspecified</pose>
		<truncated>0</truncated>
		<difficult>0</difficult>
		<bndbox>
			<xmin>956</xmin>
			<ymin>89</ymin>
			<xmax>967</xmax>
			<ymax>102</ymax>
		</bndbox>
	</object>
	<object>
    <name>person</name>
		<pose>Unspecified</pose>
		<truncated>0</truncated>
		<difficult>0</difficult>
		<bndbox>
			<xmin>986</xmin>
			<ymin>90</ymin>
			<xmax>999</xmax>
			<ymax>104</ymax>
		</bndbox>
	</object>
</annotation>