<?xml version='1.0' encoding='us-ascii'?>
<annotation>
	<folder>tmp</folder>
	<filename>part2_002182.jpg</filename>
	<path>D:\study\project\label_hat\dataset\0731\tmp\part2_002182.jpg</path>
	<source>
		<database>Unknown</database>
	</source>
	<size>
		<width>400</width>
		<height>250</height>
		<depth>3</depth>
	</size>
	<segmented>0</segmented>
	<object>
		<name>hat</name>
		<pose>Unspecified</pose>
		<truncated>0</truncated>
		<difficult>0</difficult>
		<bndbox>
			<xmin>225</xmin>
			<ymin>10</ymin>
			<xmax>262</xmax>
			<ymax>48</ymax>
		</bndbox>
	</object>
	<object>
		<name>hat</name>
		<pose>Unspecified</pose>
		<truncated>0</truncated>
		<difficult>0</difficult>
		<bndbox>
			<xmin>145</xmin>
			<ymin>25</ymin>
			<xmax>179</xmax>
			<ymax>66</ymax>
		</bndbox>
	</object>
	<object>
		<name>hat</name>
		<pose>Unspecified</pose>
		<truncated>0</truncated>
		<difficult>0</difficult>
		<bndbox>
			<xmin>101</xmin>
			<ymin>60</ymin>
			<xmax>141</xmax>
			<ymax>103</ymax>
		</bndbox>
	</object>
</annotation>