<?xml version='1.0' encoding='us-ascii'?>
<annotation>
	<folder>web_460</folder>
	<filename>PartB_02330.jpg</filename>
	<path>C:\Users\Administrator\Desktop\web_460(1)\web_460\web _421.jpeg</path>
	<source>
		<database>Unknown</database>
	</source>
	<size>
		<width>4608</width>
		<height>3072</height>
		<depth>3</depth>
	</size>
	<segmented>0</segmented>
	<object>
		<name>person</name>
		<pose>Unspecified</pose>
		<truncated>0</truncated>
		<difficult>0</difficult>
		<bndbox>
			<xmin>1134</xmin>
			<ymin>1725</ymin>
			<xmax>1430</xmax>
			<ymax>2030</ymax>
		</bndbox>
	</object>
	<object>
		<name>person</name>
		<pose>Unspecified</pose>
		<truncated>0</truncated>
		<difficult>0</difficult>
		<bndbox>
			<xmin>752</xmin>
			<ymin>1634</ymin>
			<xmax>1030</xmax>
			<ymax>1952</ymax>
		</bndbox>
	</object>
	<object>
		<name>person</name>
		<pose>Unspecified</pose>
		<truncated>0</truncated>
		<difficult>0</difficult>
		<bndbox>
			<xmin>236</xmin>
			<ymin>1595</ymin>
			<xmax>475</xmax>
			<ymax>1879</ymax>
		</bndbox>
	</object>
	<object>
		<name>person</name>
		<pose>Unspecified</pose>
		<truncated>0</truncated>
		<difficult>0</difficult>
		<bndbox>
			<xmin>234</xmin>
			<ymin>1388</ymin>
			<xmax>342</xmax>
			<ymax>1518</ymax>
		</bndbox>
	</object>
	<object>
		<name>person</name>
		<pose>Unspecified</pose>
		<truncated>0</truncated>
		<difficult>0</difficult>
		<bndbox>
			<xmin>532</xmin>
			<ymin>1331</ymin>
			<xmax>614</xmax>
			<ymax>1409</ymax>
		</bndbox>
	</object>
	<object>
		<name>person</name>
		<pose>Unspecified</pose>
		<truncated>0</truncated>
		<difficult>0</difficult>
		<bndbox>
			<xmin>578</xmin>
			<ymin>1399</ymin>
			<xmax>687</xmax>
			<ymax>1502</ymax>
		</bndbox>
	</object>
	<object>
		<name>person</name>
		<pose>Unspecified</pose>
		<truncated>0</truncated>
		<difficult>0</difficult>
		<bndbox>
			<xmin>636</xmin>
			<ymin>1352</ymin>
			<xmax>709</xmax>
			<ymax>1444</ymax>
		</bndbox>
	</object>
	<object>
		<name>person</name>
		<pose>Unspecified</pose>
		<truncated>0</truncated>
		<difficult>0</difficult>
		<bndbox>
			<xmin>766</xmin>
			<ymin>1350</ymin>
			<xmax>851</xmax>
			<ymax>1442</ymax>
		</bndbox>
	</object>
	<object>
		<name>person</name>
		<pose>Unspecified</pose>
		<truncated>0</truncated>
		<difficult>0</difficult>
		<bndbox>
			<xmin>832</xmin>
			<ymin>1350</ymin>
			<xmax>882</xmax>
			<ymax>1424</ymax>
		</bndbox>
	</object>
	<object>
		<name>person</name>
		<pose>Unspecified</pose>
		<truncated>0</truncated>
		<difficult>0</difficult>
		<bndbox>
			<xmin>892</xmin>
			<ymin>1383</ymin>
			<xmax>1001</xmax>
			<ymax>1501</ymax>
		</bndbox>
	</object>
	<object>
		<name>person</name>
		<pose>Unspecified</pose>
		<truncated>0</truncated>
		<difficult>0</difficult>
		<bndbox>
			<xmin>944</xmin>
			<ymin>1355</ymin>
			<xmax>1018</xmax>
			<ymax>1431</ymax>
		</bndbox>
	</object>
	<object>
		<name>person</name>
		<pose>Unspecified</pose>
		<truncated>0</truncated>
		<difficult>0</difficult>
		<bndbox>
			<xmin>996</xmin>
			<ymin>1358</ymin>
			<xmax>1084</xmax>
			<ymax>1454</ymax>
		</bndbox>
	</object>
	<object>
		<name>person</name>
		<pose>Unspecified</pose>
		<truncated>0</truncated>
		<difficult>0</difficult>
		<bndbox>
			<xmin>1010</xmin>
			<ymin>1397</ymin>
			<xmax>1132</xmax>
			<ymax>1539</ymax>
		</bndbox>
	</object>
	<object>
		<name>person</name>
		<pose>Unspecified</pose>
		<truncated>0</truncated>
		<difficult>0</difficult>
		<bndbox>
			<xmin>1033</xmin>
			<ymin>1328</ymin>
			<xmax>1088</xmax>
			<ymax>1402</ymax>
		</bndbox>
	</object>
	<object>
		<name>person</name>
		<pose>Unspecified</pose>
		<truncated>0</truncated>
		<difficult>0</difficult>
		<bndbox>
			<xmin>1092</xmin>
			<ymin>1359</ymin>
			<xmax>1182</xmax>
			<ymax>1465</ymax>
		</bndbox>
	</object>
	<object>
		<name>person</name>
		<pose>Unspecified</pose>
		<truncated>0</truncated>
		<difficult>0</difficult>
		<bndbox>
			<xmin>1280</xmin>
			<ymin>1408</ymin>
			<xmax>1374</xmax>
			<ymax>1518</ymax>
		</bndbox>
	</object>
	<object>
		<name>person</name>
		<pose>Unspecified</pose>
		<truncated>0</truncated>
		<difficult>0</difficult>
		<bndbox>
			<xmin>1278</xmin>
			<ymin>1352</ymin>
			<xmax>1347</xmax>
			<ymax>1419</ymax>
		</bndbox>
	</object>
	<object>
		<name>person</name>
		<pose>Unspecified</pose>
		<truncated>0</truncated>
		<difficult>0</difficult>
		<bndbox>
			<xmin>1355</xmin>
			<ymin>1359</ymin>
			<xmax>1418</xmax>
			<ymax>1432</ymax>
		</bndbox>
	</object>
	<object>
		<name>person</name>
		<pose>Unspecified</pose>
		<truncated>0</truncated>
		<difficult>0</difficult>
		<bndbox>
			<xmin>1459</xmin>
			<ymin>1362</ymin>
			<xmax>1540</xmax>
			<ymax>1457</ymax>
		</bndbox>
	</object>
	<object>
		<name>person</name>
		<pose>Unspecified</pose>
		<truncated>0</truncated>
		<difficult>0</difficult>
		<bndbox>
			<xmin>1581</xmin>
			<ymin>1524</ymin>
			<xmax>1746</xmax>
			<ymax>1709</ymax>
		</bndbox>
	</object>
	<object>
		<name>person</name>
		<pose>Unspecified</pose>
		<truncated>0</truncated>
		<difficult>0</difficult>
		<bndbox>
			<xmin>1709</xmin>
			<ymin>1428</ymin>
			<xmax>1778</xmax>
			<ymax>1519</ymax>
		</bndbox>
	</object>
	<object>
		<name>person</name>
		<pose>Unspecified</pose>
		<truncated>0</truncated>
		<difficult>0</difficult>
		<bndbox>
			<xmin>1759</xmin>
			<ymin>1395</ymin>
			<xmax>1862</xmax>
			<ymax>1515</ymax>
		</bndbox>
	</object>
	<object>
		<name>person</name>
		<pose>Unspecified</pose>
		<truncated>0</truncated>
		<difficult>0</difficult>
		<bndbox>
			<xmin>1648</xmin>
			<ymin>1408</ymin>
			<xmax>1723</xmax>
			<ymax>1488</ymax>
		</bndbox>
	</object>
	<object>
		<name>person</name>
		<pose>Unspecified</pose>
		<truncated>0</truncated>
		<difficult>0</difficult>
		<bndbox>
			<xmin>1616</xmin>
			<ymin>1388</ymin>
			<xmax>1676</xmax>
			<ymax>1457</ymax>
		</bndbox>
	</object>
	<object>
		<name>person</name>
		<pose>Unspecified</pose>
		<truncated>0</truncated>
		<difficult>0</difficult>
		<bndbox>
			<xmin>1598</xmin>
			<ymin>1347</ymin>
			<xmax>1662</xmax>
			<ymax>1415</ymax>
		</bndbox>
	</object>
	<object>
		<name>person</name>
		<pose>Unspecified</pose>
		<truncated>0</truncated>
		<difficult>0</difficult>
		<bndbox>
			<xmin>1492</xmin>
			<ymin>1350</ymin>
			<xmax>1549</xmax>
			<ymax>1409</ymax>
		</bndbox>
	</object>
	<object>
		<name>person</name>
		<pose>Unspecified</pose>
		<truncated>0</truncated>
		<difficult>0</difficult>
		<bndbox>
			<xmin>1813</xmin>
			<ymin>1361</ymin>
			<xmax>1867</xmax>
			<ymax>1428</ymax>
		</bndbox>
	</object>
	<object>
		<name>person</name>
		<pose>Unspecified</pose>
		<truncated>0</truncated>
		<difficult>0</difficult>
		<bndbox>
			<xmin>1846</xmin>
			<ymin>1378</ymin>
			<xmax>1893</xmax>
			<ymax>1448</ymax>
		</bndbox>
	</object>
	<object>
		<name>person</name>
		<pose>Unspecified</pose>
		<truncated>0</truncated>
		<difficult>0</difficult>
		<bndbox>
			<xmin>1878</xmin>
			<ymin>1408</ymin>
			<xmax>1963</xmax>
			<ymax>1489</ymax>
		</bndbox>
	</object>
	<object>
		<name>person</name>
		<pose>Unspecified</pose>
		<truncated>0</truncated>
		<difficult>0</difficult>
		<bndbox>
			<xmin>2000</xmin>
			<ymin>1407</ymin>
			<xmax>2097</xmax>
			<ymax>1510</ymax>
		</bndbox>
	</object>
	<object>
		<name>person</name>
		<pose>Unspecified</pose>
		<truncated>0</truncated>
		<difficult>0</difficult>
		<bndbox>
			<xmin>2076</xmin>
			<ymin>1392</ymin>
			<xmax>2141</xmax>
			<ymax>1469</ymax>
		</bndbox>
	</object>
	<object>
		<name>person</name>
		<pose>Unspecified</pose>
		<truncated>0</truncated>
		<difficult>0</difficult>
		<bndbox>
			<xmin>2043</xmin>
			<ymin>1378</ymin>
			<xmax>2095</xmax>
			<ymax>1428</ymax>
		</bndbox>
	</object>
	<object>
		<name>person</name>
		<pose>Unspecified</pose>
		<truncated>0</truncated>
		<difficult>0</difficult>
		<bndbox>
			<xmin>2069</xmin>
			<ymin>1352</ymin>
			<xmax>2129</xmax>
			<ymax>1415</ymax>
		</bndbox>
	</object>
	<object>
		<name>person</name>
		<pose>Unspecified</pose>
		<truncated>0</truncated>
		<difficult>0</difficult>
		<bndbox>
			<xmin>2151</xmin>
			<ymin>1403</ymin>
			<xmax>2252</xmax>
			<ymax>1515</ymax>
		</bndbox>
	</object>
	<object>
		<name>person</name>
		<pose>Unspecified</pose>
		<truncated>0</truncated>
		<difficult>0</difficult>
		<bndbox>
			<xmin>2153</xmin>
			<ymin>1368</ymin>
			<xmax>2210</xmax>
			<ymax>1442</ymax>
		</bndbox>
	</object>
	<object>
		<name>person</name>
		<pose>Unspecified</pose>
		<truncated>0</truncated>
		<difficult>0</difficult>
		<bndbox>
			<xmin>2212</xmin>
			<ymin>1376</ymin>
			<xmax>2257</xmax>
			<ymax>1431</ymax>
		</bndbox>
	</object>
	<object>
		<name>person</name>
		<pose>Unspecified</pose>
		<truncated>0</truncated>
		<difficult>0</difficult>
		<bndbox>
			<xmin>2247</xmin>
			<ymin>1392</ymin>
			<xmax>2293</xmax>
			<ymax>1450</ymax>
		</bndbox>
	</object>
	<object>
		<name>person</name>
		<pose>Unspecified</pose>
		<truncated>0</truncated>
		<difficult>0</difficult>
		<bndbox>
			<xmin>2240</xmin>
			<ymin>1351</ymin>
			<xmax>2290</xmax>
			<ymax>1409</ymax>
		</bndbox>
	</object>
	<object>
		<name>person</name>
		<pose>Unspecified</pose>
		<truncated>0</truncated>
		<difficult>0</difficult>
		<bndbox>
			<xmin>2309</xmin>
			<ymin>1370</ymin>
			<xmax>2349</xmax>
			<ymax>1426</ymax>
		</bndbox>
	</object>
	<object>
		<name>person</name>
		<pose>Unspecified</pose>
		<truncated>0</truncated>
		<difficult>0</difficult>
		<bndbox>
			<xmin>2343</xmin>
			<ymin>1386</ymin>
			<xmax>2400</xmax>
			<ymax>1466</ymax>
		</bndbox>
	</object>
	<object>
		<name>person</name>
		<pose>Unspecified</pose>
		<truncated>0</truncated>
		<difficult>0</difficult>
		<bndbox>
			<xmin>2120</xmin>
			<ymin>1555</ymin>
			<xmax>2330</xmax>
			<ymax>1820</ymax>
		</bndbox>
	</object>
	<object>
		<name>person</name>
		<pose>Unspecified</pose>
		<truncated>0</truncated>
		<difficult>0</difficult>
		<bndbox>
			<xmin>2529</xmin>
			<ymin>1946</ymin>
			<xmax>2895</xmax>
			<ymax>2318</ymax>
		</bndbox>
	</object>
	<object>
		<name>person</name>
		<pose>Unspecified</pose>
		<truncated>0</truncated>
		<difficult>0</difficult>
		<bndbox>
			<xmin>2490</xmin>
			<ymin>1526</ymin>
			<xmax>2618</xmax>
			<ymax>1670</ymax>
		</bndbox>
	</object>
	<object>
		<name>person</name>
		<pose>Unspecified</pose>
		<truncated>0</truncated>
		<difficult>0</difficult>
		<bndbox>
			<xmin>2476</xmin>
			<ymin>1475</ymin>
			<xmax>2563</xmax>
			<ymax>1569</ymax>
		</bndbox>
	</object>
	<object>
		<name>person</name>
		<pose>Unspecified</pose>
		<truncated>0</truncated>
		<difficult>0</difficult>
		<bndbox>
			<xmin>2473</xmin>
			<ymin>1384</ymin>
			<xmax>2543</xmax>
			<ymax>1467</ymax>
		</bndbox>
	</object>
	<object>
		<name>person</name>
		<pose>Unspecified</pose>
		<truncated>0</truncated>
		<difficult>0</difficult>
		<bndbox>
			<xmin>2414</xmin>
			<ymin>1374</ymin>
			<xmax>2467</xmax>
			<ymax>1434</ymax>
		</bndbox>
	</object>
	<object>
		<name>person</name>
		<pose>Unspecified</pose>
		<truncated>0</truncated>
		<difficult>0</difficult>
		<bndbox>
			<xmin>2526</xmin>
			<ymin>1375</ymin>
			<xmax>2562</xmax>
			<ymax>1415</ymax>
		</bndbox>
	</object>
	<object>
		<name>person</name>
		<pose>Unspecified</pose>
		<truncated>0</truncated>
		<difficult>0</difficult>
		<bndbox>
			<xmin>2552</xmin>
			<ymin>1378</ymin>
			<xmax>2600</xmax>
			<ymax>1442</ymax>
		</bndbox>
	</object>
	<object>
		<name>person</name>
		<pose>Unspecified</pose>
		<truncated>0</truncated>
		<difficult>0</difficult>
		<bndbox>
			<xmin>2604</xmin>
			<ymin>1374</ymin>
			<xmax>2642</xmax>
			<ymax>1422</ymax>
		</bndbox>
	</object>
	<object>
		<name>person</name>
		<pose>Unspecified</pose>
		<truncated>0</truncated>
		<difficult>0</difficult>
		<bndbox>
			<xmin>2642</xmin>
			<ymin>1362</ymin>
			<xmax>2697</xmax>
			<ymax>1428</ymax>
		</bndbox>
	</object>
	<object>
		<name>person</name>
		<pose>Unspecified</pose>
		<truncated>0</truncated>
		<difficult>0</difficult>
		<bndbox>
			<xmin>2654</xmin>
			<ymin>1401</ymin>
			<xmax>2729</xmax>
			<ymax>1489</ymax>
		</bndbox>
	</object>
	<object>
		<name>person</name>
		<pose>Unspecified</pose>
		<truncated>0</truncated>
		<difficult>0</difficult>
		<bndbox>
			<xmin>2787</xmin>
			<ymin>1596</ymin>
			<xmax>2945</xmax>
			<ymax>1730</ymax>
		</bndbox>
	</object>
	<object>
		<name>person</name>
		<pose>Unspecified</pose>
		<truncated>0</truncated>
		<difficult>0</difficult>
		<bndbox>
			<xmin>2981</xmin>
			<ymin>1495</ymin>
			<xmax>3120</xmax>
			<ymax>1643</ymax>
		</bndbox>
	</object>
	<object>
		<name>person</name>
		<pose>Unspecified</pose>
		<truncated>0</truncated>
		<difficult>0</difficult>
		<bndbox>
			<xmin>3301</xmin>
			<ymin>1594</ymin>
			<xmax>3459</xmax>
			<ymax>1757</ymax>
		</bndbox>
	</object>
	<object>
		<name>person</name>
		<pose>Unspecified</pose>
		<truncated>0</truncated>
		<difficult>0</difficult>
		<bndbox>
			<xmin>3746</xmin>
			<ymin>1718</ymin>
			<xmax>3995</xmax>
			<ymax>1948</ymax>
		</bndbox>
	</object>
	<object>
		<name>person</name>
		<pose>Unspecified</pose>
		<truncated>0</truncated>
		<difficult>0</difficult>
		<bndbox>
			<xmin>3733</xmin>
			<ymin>1520</ymin>
			<xmax>3868</xmax>
			<ymax>1657</ymax>
		</bndbox>
	</object>
	<object>
		<name>person</name>
		<pose>Unspecified</pose>
		<truncated>0</truncated>
		<difficult>0</difficult>
		<bndbox>
			<xmin>3989</xmin>
			<ymin>1623</ymin>
			<xmax>4136</xmax>
			<ymax>1763</ymax>
		</bndbox>
	</object>
	<object>
		<name>person</name>
		<pose>Unspecified</pose>
		<truncated>0</truncated>
		<difficult>0</difficult>
		<bndbox>
			<xmin>4104</xmin>
			<ymin>1561</ymin>
			<xmax>4245</xmax>
			<ymax>1708</ymax>
		</bndbox>
	</object>
	<object>
		<name>person</name>
		<pose>Unspecified</pose>
		<truncated>0</truncated>
		<difficult>0</difficult>
		<bndbox>
			<xmin>4308</xmin>
			<ymin>1450</ymin>
			<xmax>4353</xmax>
			<ymax>1517</ymax>
		</bndbox>
	</object>
	<object>
		<name>person</name>
		<pose>Unspecified</pose>
		<truncated>0</truncated>
		<difficult>0</difficult>
		<bndbox>
			<xmin>4251</xmin>
			<ymin>1459</ymin>
			<xmax>4305</xmax>
			<ymax>1529</ymax>
		</bndbox>
	</object>
	<object>
		<name>person</name>
		<pose>Unspecified</pose>
		<truncated>0</truncated>
		<difficult>0</difficult>
		<bndbox>
			<xmin>4177</xmin>
			<ymin>1456</ymin>
			<xmax>4231</xmax>
			<ymax>1520</ymax>
		</bndbox>
	</object>
	<object>
		<name>person</name>
		<pose>Unspecified</pose>
		<truncated>0</truncated>
		<difficult>0</difficult>
		<bndbox>
			<xmin>4104</xmin>
			<ymin>1464</ymin>
			<xmax>4164</xmax>
			<ymax>1530</ymax>
		</bndbox>
	</object>
	<object>
		<name>person</name>
		<pose>Unspecified</pose>
		<truncated>0</truncated>
		<difficult>0</difficult>
		<bndbox>
			<xmin>4136</xmin>
			<ymin>1441</ymin>
			<xmax>4184</xmax>
			<ymax>1494</ymax>
		</bndbox>
	</object>
	<object>
		<name>person</name>
		<pose>Unspecified</pose>
		<truncated>0</truncated>
		<difficult>0</difficult>
		<bndbox>
			<xmin>4032</xmin>
			<ymin>1453</ymin>
			<xmax>4091</xmax>
			<ymax>1510</ymax>
		</bndbox>
	</object>
	<object>
		<name>person</name>
		<pose>Unspecified</pose>
		<truncated>0</truncated>
		<difficult>0</difficult>
		<bndbox>
			<xmin>3981</xmin>
			<ymin>1429</ymin>
			<xmax>4030</xmax>
			<ymax>1480</ymax>
		</bndbox>
	</object>
	<object>
		<name>person</name>
		<pose>Unspecified</pose>
		<truncated>0</truncated>
		<difficult>0</difficult>
		<bndbox>
			<xmin>3954</xmin>
			<ymin>1452</ymin>
			<xmax>4001</xmax>
			<ymax>1507</ymax>
		</bndbox>
	</object>
	<object>
		<name>person</name>
		<pose>Unspecified</pose>
		<truncated>0</truncated>
		<difficult>0</difficult>
		<bndbox>
			<xmin>3903</xmin>
			<ymin>1463</ymin>
			<xmax>3970</xmax>
			<ymax>1542</ymax>
		</bndbox>
	</object>
	<object>
		<name>person</name>
		<pose>Unspecified</pose>
		<truncated>0</truncated>
		<difficult>0</difficult>
		<bndbox>
			<xmin>3855</xmin>
			<ymin>1433</ymin>
			<xmax>3908</xmax>
			<ymax>1488</ymax>
		</bndbox>
	</object>
	<object>
		<name>person</name>
		<pose>Unspecified</pose>
		<truncated>0</truncated>
		<difficult>0</difficult>
		<bndbox>
			<xmin>3791</xmin>
			<ymin>1440</ymin>
			<xmax>3852</xmax>
			<ymax>1512</ymax>
		</bndbox>
	</object>
	<object>
		<name>person</name>
		<pose>Unspecified</pose>
		<truncated>0</truncated>
		<difficult>0</difficult>
		<bndbox>
			<xmin>3724</xmin>
			<ymin>1422</ymin>
			<xmax>3775</xmax>
			<ymax>1483</ymax>
		</bndbox>
	</object>
	<object>
		<name>person</name>
		<pose>Unspecified</pose>
		<truncated>0</truncated>
		<difficult>0</difficult>
		<bndbox>
			<xmin>3659</xmin>
			<ymin>1426</ymin>
			<xmax>3722</xmax>
			<ymax>1502</ymax>
		</bndbox>
	</object>
	<object>
		<name>person</name>
		<pose>Unspecified</pose>
		<truncated>0</truncated>
		<difficult>0</difficult>
		<bndbox>
			<xmin>3622</xmin>
			<ymin>1423</ymin>
			<xmax>3684</xmax>
			<ymax>1504</ymax>
		</bndbox>
	</object>
	<object>
		<name>person</name>
		<pose>Unspecified</pose>
		<truncated>0</truncated>
		<difficult>0</difficult>
		<bndbox>
			<xmin>3588</xmin>
			<ymin>1440</ymin>
			<xmax>3635</xmax>
			<ymax>1494</ymax>
		</bndbox>
	</object>
	<object>
		<name>person</name>
		<pose>Unspecified</pose>
		<truncated>0</truncated>
		<difficult>0</difficult>
		<bndbox>
			<xmin>3481</xmin>
			<ymin>1432</ymin>
			<xmax>3543</xmax>
			<ymax>1511</ymax>
		</bndbox>
	</object>
	<object>
		<name>person</name>
		<pose>Unspecified</pose>
		<truncated>0</truncated>
		<difficult>0</difficult>
		<bndbox>
			<xmin>3187</xmin>
			<ymin>1395</ymin>
			<xmax>3243</xmax>
			<ymax>1461</ymax>
		</bndbox>
	</object>
	<object>
		<name>person</name>
		<pose>Unspecified</pose>
		<truncated>0</truncated>
		<difficult>0</difficult>
		<bndbox>
			<xmin>2777</xmin>
			<ymin>1386</ymin>
			<xmax>2824</xmax>
			<ymax>1432</ymax>
		</bndbox>
	</object>
	<object>
		<name>person</name>
		<pose>Unspecified</pose>
		<truncated>0</truncated>
		<difficult>0</difficult>
		<bndbox>
			<xmin>2862</xmin>
			<ymin>1395</ymin>
			<xmax>2919</xmax>
			<ymax>1448</ymax>
		</bndbox>
	</object>
	<object>
		<name>person</name>
		<pose>Unspecified</pose>
		<truncated>0</truncated>
		<difficult>0</difficult>
		<bndbox>
			<xmin>2923</xmin>
			<ymin>1388</ymin>
			<xmax>2975</xmax>
			<ymax>1454</ymax>
		</bndbox>
	</object>
	<object>
		<name>person</name>
		<pose>Unspecified</pose>
		<truncated>0</truncated>
		<difficult>0</difficult>
		<bndbox>
			<xmin>2968</xmin>
			<ymin>1402</ymin>
			<xmax>3018</xmax>
			<ymax>1464</ymax>
		</bndbox>
	</object>
	<object>
		<name>person</name>
		<pose>Unspecified</pose>
		<truncated>0</truncated>
		<difficult>0</difficult>
		<bndbox>
			<xmin>3026</xmin>
			<ymin>1393</ymin>
			<xmax>3076</xmax>
			<ymax>1452</ymax>
		</bndbox>
	</object>
	<object>
		<name>person</name>
		<pose>Unspecified</pose>
		<truncated>0</truncated>
		<difficult>0</difficult>
		<bndbox>
			<xmin>3137</xmin>
			<ymin>1389</ymin>
			<xmax>3193</xmax>
			<ymax>1447</ymax>
		</bndbox>
	</object>
</annotation>