<?xml version='1.0' encoding='us-ascii'?>
<annotation>
	<folder>750-999</folder>
	<filename>PartA_00811.jpg</filename>
	<path>/media/zrcai/study/lab/0818data/750-999/750-999/811.jpg</path>
	<source>
		<database>Unknown</database>
	</source>
	<size>
		<width>1009</width>
		<height>569</height>
		<depth>3</depth>
	</size>
	<segmented>0</segmented>
	<object>
    <name>person</name>
		<pose>Unspecified</pose>
		<truncated>0</truncated>
		<difficult>0</difficult>
		<bndbox>
			<xmin>891</xmin>
			<ymin>116</ymin>
			<xmax>904</xmax>
			<ymax>138</ymax>
		</bndbox>
	</object>
	<object>
    <name>person</name>
		<pose>Unspecified</pose>
		<truncated>0</truncated>
		<difficult>0</difficult>
		<bndbox>
			<xmin>752</xmin>
			<ymin>74</ymin>
			<xmax>763</xmax>
			<ymax>93</ymax>
		</bndbox>
	</object>
	<object>
    <name>person</name>
		<pose>Unspecified</pose>
		<truncated>0</truncated>
		<difficult>0</difficult>
		<bndbox>
			<xmin>766</xmin>
			<ymin>83</ymin>
			<xmax>778</xmax>
			<ymax>98</ymax>
		</bndbox>
	</object>
	<object>
    <name>person</name>
		<pose>Unspecified</pose>
		<truncated>0</truncated>
		<difficult>0</difficult>
		<bndbox>
			<xmin>642</xmin>
			<ymin>65</ymin>
			<xmax>654</xmax>
			<ymax>82</ymax>
		</bndbox>
	</object>
	<object>
    <name>person</name>
		<pose>Unspecified</pose>
		<truncated>0</truncated>
		<difficult>0</difficult>
		<bndbox>
			<xmin>547</xmin>
			<ymin>34</ymin>
			<xmax>557</xmax>
			<ymax>47</ymax>
		</bndbox>
	</object>
	<object>
    <name>person</name>
		<pose>Unspecified</pose>
		<truncated>0</truncated>
		<difficult>0</difficult>
		<bndbox>
			<xmin>598</xmin>
			<ymin>33</ymin>
			<xmax>607</xmax>
			<ymax>47</ymax>
		</bndbox>
	</object>
</annotation>