<?xml version='1.0' encoding='us-ascii'?>
<annotation>
	<folder>tmp</folder>
	<filename>part2_001480.jpg</filename>
	<path>H:\dataset\0730_2\0730\tmp\part2_001480.jpg</path>
	<source>
		<database>Unknown</database>
	</source>
	<size>
		<width>270</width>
		<height>270</height>
		<depth>3</depth>
	</size>
	<segmented>0</segmented>
	<object>
		<name>hat</name>
		<pose>Unspecified</pose>
		<truncated>0</truncated>
		<difficult>0</difficult>
		<bndbox>
			<xmin>15</xmin>
			<ymin>75</ymin>
			<xmax>92</xmax>
			<ymax>163</ymax>
		</bndbox>
	</object>
	<object>
		<name>hat</name>
		<pose>Unspecified</pose>
		<truncated>1</truncated>
		<difficult>0</difficult>
		<bndbox>
			<xmin>195</xmin>
			<ymin>139</ymin>
			<xmax>270</xmax>
			<ymax>212</ymax>
		</bndbox>
	</object>
</annotation>