<?xml version='1.0' encoding='us-ascii'?>
<annotation>
	<folder>500pic</folder>
	<filename>PartA_01532.jpg</filename>
	<path>C:\Users\Administrator\Desktop\500pic\500pic\01532.jpg</path>
	<source>
		<database>Unknown</database>
	</source>
	<size>
		<width>1238</width>
		<height>708</height>
		<depth>3</depth>
	</size>
	<segmented>0</segmented>
	<object>
		<name>person</name>
		<pose>Unspecified</pose>
		<truncated>0</truncated>
		<difficult>0</difficult>
		<bndbox>
			<xmin>57</xmin>
			<ymin>280</ymin>
			<xmax>106</xmax>
			<ymax>330</ymax>
		</bndbox>
	</object>
	<object>
		<name>person</name>
		<pose>Unspecified</pose>
		<truncated>0</truncated>
		<difficult>0</difficult>
		<bndbox>
			<xmin>349</xmin>
			<ymin>174</ymin>
			<xmax>377</xmax>
			<ymax>207</ymax>
		</bndbox>
	</object>
	<object>
		<name>person</name>
		<pose>Unspecified</pose>
		<truncated>0</truncated>
		<difficult>0</difficult>
		<bndbox>
			<xmin>400</xmin>
			<ymin>173</ymin>
			<xmax>424</xmax>
			<ymax>203</ymax>
		</bndbox>
	</object>
	<object>
		<name>person</name>
		<pose>Unspecified</pose>
		<truncated>0</truncated>
		<difficult>0</difficult>
		<bndbox>
			<xmin>381</xmin>
			<ymin>152</ymin>
			<xmax>404</xmax>
			<ymax>181</ymax>
		</bndbox>
	</object>
	<object>
		<name>person</name>
		<pose>Unspecified</pose>
		<truncated>0</truncated>
		<difficult>0</difficult>
		<bndbox>
			<xmin>423</xmin>
			<ymin>135</ymin>
			<xmax>447</xmax>
			<ymax>162</ymax>
		</bndbox>
	</object>
	<object>
		<name>person</name>
		<pose>Unspecified</pose>
		<truncated>0</truncated>
		<difficult>0</difficult>
		<bndbox>
			<xmin>432</xmin>
			<ymin>149</ymin>
			<xmax>455</xmax>
			<ymax>172</ymax>
		</bndbox>
	</object>
	<object>
		<name>person</name>
		<pose>Unspecified</pose>
		<truncated>0</truncated>
		<difficult>0</difficult>
		<bndbox>
			<xmin>451</xmin>
			<ymin>165</ymin>
			<xmax>475</xmax>
			<ymax>196</ymax>
		</bndbox>
	</object>
	<object>
		<name>person</name>
		<pose>Unspecified</pose>
		<truncated>0</truncated>
		<difficult>0</difficult>
		<bndbox>
			<xmin>494</xmin>
			<ymin>186</ymin>
			<xmax>521</xmax>
			<ymax>217</ymax>
		</bndbox>
	</object>
	<object>
		<name>person</name>
		<pose>Unspecified</pose>
		<truncated>0</truncated>
		<difficult>0</difficult>
		<bndbox>
			<xmin>485</xmin>
			<ymin>175</ymin>
			<xmax>508</xmax>
			<ymax>202</ymax>
		</bndbox>
	</object>
	<object>
		<name>person</name>
		<pose>Unspecified</pose>
		<truncated>0</truncated>
		<difficult>0</difficult>
		<bndbox>
			<xmin>465</xmin>
			<ymin>146</ymin>
			<xmax>490</xmax>
			<ymax>176</ymax>
		</bndbox>
	</object>
	<object>
		<name>person</name>
		<pose>Unspecified</pose>
		<truncated>0</truncated>
		<difficult>0</difficult>
		<bndbox>
			<xmin>491</xmin>
			<ymin>147</ymin>
			<xmax>513</xmax>
			<ymax>170</ymax>
		</bndbox>
	</object>
	<object>
		<name>person</name>
		<pose>Unspecified</pose>
		<truncated>0</truncated>
		<difficult>0</difficult>
		<bndbox>
			<xmin>504</xmin>
			<ymin>125</ymin>
			<xmax>525</xmax>
			<ymax>151</ymax>
		</bndbox>
	</object>
	<object>
		<name>person</name>
		<pose>Unspecified</pose>
		<truncated>0</truncated>
		<difficult>0</difficult>
		<bndbox>
			<xmin>544</xmin>
			<ymin>139</ymin>
			<xmax>568</xmax>
			<ymax>167</ymax>
		</bndbox>
	</object>
	<object>
		<name>person</name>
		<pose>Unspecified</pose>
		<truncated>0</truncated>
		<difficult>0</difficult>
		<bndbox>
			<xmin>558</xmin>
			<ymin>122</ymin>
			<xmax>579</xmax>
			<ymax>149</ymax>
		</bndbox>
	</object>
	<object>
		<name>person</name>
		<pose>Unspecified</pose>
		<truncated>0</truncated>
		<difficult>0</difficult>
		<bndbox>
			<xmin>597</xmin>
			<ymin>143</ymin>
			<xmax>623</xmax>
			<ymax>173</ymax>
		</bndbox>
	</object>
	<object>
		<name>person</name>
		<pose>Unspecified</pose>
		<truncated>0</truncated>
		<difficult>0</difficult>
		<bndbox>
			<xmin>528</xmin>
			<ymin>112</ymin>
			<xmax>552</xmax>
			<ymax>141</ymax>
		</bndbox>
	</object>
	<object>
		<name>person</name>
		<pose>Unspecified</pose>
		<truncated>0</truncated>
		<difficult>0</difficult>
		<bndbox>
			<xmin>574</xmin>
			<ymin>105</ymin>
			<xmax>592</xmax>
			<ymax>124</ymax>
		</bndbox>
	</object>
	<object>
		<name>person</name>
		<pose>Unspecified</pose>
		<truncated>0</truncated>
		<difficult>0</difficult>
		<bndbox>
			<xmin>576</xmin>
			<ymin>92</ymin>
			<xmax>593</xmax>
			<ymax>110</ymax>
		</bndbox>
	</object>
	<object>
		<name>person</name>
		<pose>Unspecified</pose>
		<truncated>0</truncated>
		<difficult>0</difficult>
		<bndbox>
			<xmin>588</xmin>
			<ymin>89</ymin>
			<xmax>602</xmax>
			<ymax>108</ymax>
		</bndbox>
	</object>
	<object>
		<name>person</name>
		<pose>Unspecified</pose>
		<truncated>0</truncated>
		<difficult>0</difficult>
		<bndbox>
			<xmin>622</xmin>
			<ymin>120</ymin>
			<xmax>646</xmax>
			<ymax>148</ymax>
		</bndbox>
	</object>
	<object>
		<name>person</name>
		<pose>Unspecified</pose>
		<truncated>0</truncated>
		<difficult>0</difficult>
		<bndbox>
			<xmin>628</xmin>
			<ymin>104</ymin>
			<xmax>652</xmax>
			<ymax>128</ymax>
		</bndbox>
	</object>
	<object>
		<name>person</name>
		<pose>Unspecified</pose>
		<truncated>0</truncated>
		<difficult>0</difficult>
		<bndbox>
			<xmin>621</xmin>
			<ymin>97</ymin>
			<xmax>638</xmax>
			<ymax>115</ymax>
		</bndbox>
	</object>
	<object>
		<name>person</name>
		<pose>Unspecified</pose>
		<truncated>0</truncated>
		<difficult>0</difficult>
		<bndbox>
			<xmin>628</xmin>
			<ymin>86</ymin>
			<xmax>647</xmax>
			<ymax>105</ymax>
		</bndbox>
	</object>
	<object>
		<name>person</name>
		<pose>Unspecified</pose>
		<truncated>0</truncated>
		<difficult>0</difficult>
		<bndbox>
			<xmin>643</xmin>
			<ymin>90</ymin>
			<xmax>659</xmax>
			<ymax>112</ymax>
		</bndbox>
	</object>
	<object>
		<name>person</name>
		<pose>Unspecified</pose>
		<truncated>0</truncated>
		<difficult>0</difficult>
		<bndbox>
			<xmin>668</xmin>
			<ymin>84</ymin>
			<xmax>685</xmax>
			<ymax>103</ymax>
		</bndbox>
	</object>
	<object>
		<name>person</name>
		<pose>Unspecified</pose>
		<truncated>0</truncated>
		<difficult>0</difficult>
		<bndbox>
			<xmin>669</xmin>
			<ymin>111</ymin>
			<xmax>692</xmax>
			<ymax>137</ymax>
		</bndbox>
	</object>
	<object>
		<name>person</name>
		<pose>Unspecified</pose>
		<truncated>0</truncated>
		<difficult>0</difficult>
		<bndbox>
			<xmin>694</xmin>
			<ymin>88</ymin>
			<xmax>714</xmax>
			<ymax>110</ymax>
		</bndbox>
	</object>
	<object>
		<name>person</name>
		<pose>Unspecified</pose>
		<truncated>0</truncated>
		<difficult>0</difficult>
		<bndbox>
			<xmin>725</xmin>
			<ymin>102</ymin>
			<xmax>750</xmax>
			<ymax>126</ymax>
		</bndbox>
	</object>
	<object>
		<name>person</name>
		<pose>Unspecified</pose>
		<truncated>0</truncated>
		<difficult>0</difficult>
		<bndbox>
			<xmin>719</xmin>
			<ymin>92</ymin>
			<xmax>737</xmax>
			<ymax>114</ymax>
		</bndbox>
	</object>
	<object>
		<name>person</name>
		<pose>Unspecified</pose>
		<truncated>0</truncated>
		<difficult>0</difficult>
		<bndbox>
			<xmin>699</xmin>
			<ymin>74</ymin>
			<xmax>719</xmax>
			<ymax>94</ymax>
		</bndbox>
	</object>
	<object>
		<name>person</name>
		<pose>Unspecified</pose>
		<truncated>0</truncated>
		<difficult>0</difficult>
		<bndbox>
			<xmin>731</xmin>
			<ymin>74</ymin>
			<xmax>751</xmax>
			<ymax>100</ymax>
		</bndbox>
	</object>
	<object>
		<name>person</name>
		<pose>Unspecified</pose>
		<truncated>0</truncated>
		<difficult>0</difficult>
		<bndbox>
			<xmin>772</xmin>
			<ymin>85</ymin>
			<xmax>793</xmax>
			<ymax>111</ymax>
		</bndbox>
	</object>
	<object>
		<name>person</name>
		<pose>Unspecified</pose>
		<truncated>0</truncated>
		<difficult>0</difficult>
		<bndbox>
			<xmin>763</xmin>
			<ymin>73</ymin>
			<xmax>780</xmax>
			<ymax>96</ymax>
		</bndbox>
	</object>
	<object>
		<name>person</name>
		<pose>Unspecified</pose>
		<truncated>0</truncated>
		<difficult>0</difficult>
		<bndbox>
			<xmin>766</xmin>
			<ymin>61</ymin>
			<xmax>783</xmax>
			<ymax>76</ymax>
		</bndbox>
	</object>
	<object>
		<name>person</name>
		<pose>Unspecified</pose>
		<truncated>0</truncated>
		<difficult>0</difficult>
		<bndbox>
			<xmin>791</xmin>
			<ymin>76</ymin>
			<xmax>806</xmax>
			<ymax>98</ymax>
		</bndbox>
	</object>
	<object>
		<name>person</name>
		<pose>Unspecified</pose>
		<truncated>0</truncated>
		<difficult>0</difficult>
		<bndbox>
			<xmin>814</xmin>
			<ymin>78</ymin>
			<xmax>831</xmax>
			<ymax>101</ymax>
		</bndbox>
	</object>
	<object>
		<name>person</name>
		<pose>Unspecified</pose>
		<truncated>0</truncated>
		<difficult>0</difficult>
		<bndbox>
			<xmin>810</xmin>
			<ymin>59</ymin>
			<xmax>826</xmax>
			<ymax>79</ymax>
		</bndbox>
	</object>
	<object>
		<name>person</name>
		<pose>Unspecified</pose>
		<truncated>0</truncated>
		<difficult>0</difficult>
		<bndbox>
			<xmin>830</xmin>
			<ymin>60</ymin>
			<xmax>849</xmax>
			<ymax>78</ymax>
		</bndbox>
	</object>
	<object>
		<name>person</name>
		<pose>Unspecified</pose>
		<truncated>0</truncated>
		<difficult>0</difficult>
		<bndbox>
			<xmin>836</xmin>
			<ymin>75</ymin>
			<xmax>850</xmax>
			<ymax>97</ymax>
		</bndbox>
	</object>
	<object>
		<name>person</name>
		<pose>Unspecified</pose>
		<truncated>0</truncated>
		<difficult>0</difficult>
		<bndbox>
			<xmin>873</xmin>
			<ymin>68</ymin>
			<xmax>892</xmax>
			<ymax>87</ymax>
		</bndbox>
	</object>
	<object>
		<name>person</name>
		<pose>Unspecified</pose>
		<truncated>0</truncated>
		<difficult>0</difficult>
		<bndbox>
			<xmin>662</xmin>
			<ymin>179</ymin>
			<xmax>704</xmax>
			<ymax>224</ymax>
		</bndbox>
	</object>
	<object>
		<name>person</name>
		<pose>Unspecified</pose>
		<truncated>0</truncated>
		<difficult>0</difficult>
		<bndbox>
			<xmin>690</xmin>
			<ymin>149</ymin>
			<xmax>721</xmax>
			<ymax>187</ymax>
		</bndbox>
	</object>
	<object>
		<name>person</name>
		<pose>Unspecified</pose>
		<truncated>0</truncated>
		<difficult>0</difficult>
		<bndbox>
			<xmin>737</xmin>
			<ymin>204</ymin>
			<xmax>777</xmax>
			<ymax>252</ymax>
		</bndbox>
	</object>
	<object>
		<name>person</name>
		<pose>Unspecified</pose>
		<truncated>0</truncated>
		<difficult>0</difficult>
		<bndbox>
			<xmin>761</xmin>
			<ymin>154</ymin>
			<xmax>790</xmax>
			<ymax>192</ymax>
		</bndbox>
	</object>
	<object>
		<name>person</name>
		<pose>Unspecified</pose>
		<truncated>0</truncated>
		<difficult>0</difficult>
		<bndbox>
			<xmin>761</xmin>
			<ymin>136</ymin>
			<xmax>791</xmax>
			<ymax>167</ymax>
		</bndbox>
	</object>
	<object>
		<name>person</name>
		<pose>Unspecified</pose>
		<truncated>0</truncated>
		<difficult>0</difficult>
		<bndbox>
			<xmin>843</xmin>
			<ymin>138</ymin>
			<xmax>865</xmax>
			<ymax>173</ymax>
		</bndbox>
	</object>
	<object>
		<name>person</name>
		<pose>Unspecified</pose>
		<truncated>0</truncated>
		<difficult>0</difficult>
		<bndbox>
			<xmin>831</xmin>
			<ymin>176</ymin>
			<xmax>859</xmax>
			<ymax>220</ymax>
		</bndbox>
	</object>
	<object>
		<name>person</name>
		<pose>Unspecified</pose>
		<truncated>0</truncated>
		<difficult>0</difficult>
		<bndbox>
			<xmin>882</xmin>
			<ymin>139</ymin>
			<xmax>912</xmax>
			<ymax>179</ymax>
		</bndbox>
	</object>
	<object>
		<name>person</name>
		<pose>Unspecified</pose>
		<truncated>0</truncated>
		<difficult>0</difficult>
		<bndbox>
			<xmin>845</xmin>
			<ymin>118</ymin>
			<xmax>866</xmax>
			<ymax>142</ymax>
		</bndbox>
	</object>
	<object>
		<name>person</name>
		<pose>Unspecified</pose>
		<truncated>0</truncated>
		<difficult>0</difficult>
		<bndbox>
			<xmin>878</xmin>
			<ymin>90</ymin>
			<xmax>899</xmax>
			<ymax>118</ymax>
		</bndbox>
	</object>
	<object>
		<name>person</name>
		<pose>Unspecified</pose>
		<truncated>0</truncated>
		<difficult>0</difficult>
		<bndbox>
			<xmin>904</xmin>
			<ymin>117</ymin>
			<xmax>931</xmax>
			<ymax>149</ymax>
		</bndbox>
	</object>
	<object>
		<name>person</name>
		<pose>Unspecified</pose>
		<truncated>0</truncated>
		<difficult>0</difficult>
		<bndbox>
			<xmin>945</xmin>
			<ymin>184</ymin>
			<xmax>976</xmax>
			<ymax>232</ymax>
		</bndbox>
	</object>
	<object>
		<name>person</name>
		<pose>Unspecified</pose>
		<truncated>0</truncated>
		<difficult>0</difficult>
		<bndbox>
			<xmin>936</xmin>
			<ymin>148</ymin>
			<xmax>969</xmax>
			<ymax>191</ymax>
		</bndbox>
	</object>
	<object>
		<name>person</name>
		<pose>Unspecified</pose>
		<truncated>0</truncated>
		<difficult>0</difficult>
		<bndbox>
			<xmin>964</xmin>
			<ymin>132</ymin>
			<xmax>988</xmax>
			<ymax>162</ymax>
		</bndbox>
	</object>
	<object>
		<name>person</name>
		<pose>Unspecified</pose>
		<truncated>0</truncated>
		<difficult>0</difficult>
		<bndbox>
			<xmin>919</xmin>
			<ymin>83</ymin>
			<xmax>936</xmax>
			<ymax>105</ymax>
		</bndbox>
	</object>
	<object>
		<name>person</name>
		<pose>Unspecified</pose>
		<truncated>0</truncated>
		<difficult>0</difficult>
		<bndbox>
			<xmin>1051</xmin>
			<ymin>153</ymin>
			<xmax>1079</xmax>
			<ymax>187</ymax>
		</bndbox>
	</object>
	<object>
		<name>person</name>
		<pose>Unspecified</pose>
		<truncated>0</truncated>
		<difficult>0</difficult>
		<bndbox>
			<xmin>1032</xmin>
			<ymin>204</ymin>
			<xmax>1066</xmax>
			<ymax>249</ymax>
		</bndbox>
	</object>
	<object>
		<name>person</name>
		<pose>Unspecified</pose>
		<truncated>0</truncated>
		<difficult>0</difficult>
		<bndbox>
			<xmin>1005</xmin>
			<ymin>243</ymin>
			<xmax>1051</xmax>
			<ymax>304</ymax>
		</bndbox>
	</object>
	<object>
		<name>person</name>
		<pose>Unspecified</pose>
		<truncated>0</truncated>
		<difficult>0</difficult>
		<bndbox>
			<xmin>1101</xmin>
			<ymin>277</ymin>
			<xmax>1139</xmax>
			<ymax>335</ymax>
		</bndbox>
	</object>
	<object>
		<name>person</name>
		<pose>Unspecified</pose>
		<truncated>0</truncated>
		<difficult>0</difficult>
		<bndbox>
			<xmin>1016</xmin>
			<ymin>160</ymin>
			<xmax>1038</xmax>
			<ymax>191</ymax>
		</bndbox>
	</object>
	<object>
		<name>person</name>
		<pose>Unspecified</pose>
		<truncated>0</truncated>
		<difficult>0</difficult>
		<bndbox>
			<xmin>1124</xmin>
			<ymin>213</ymin>
			<xmax>1162</xmax>
			<ymax>265</ymax>
		</bndbox>
	</object>
	<object>
		<name>person</name>
		<pose>Unspecified</pose>
		<truncated>0</truncated>
		<difficult>0</difficult>
		<bndbox>
			<xmin>1144</xmin>
			<ymin>152</ymin>
			<xmax>1168</xmax>
			<ymax>184</ymax>
		</bndbox>
	</object>
	<object>
		<name>person</name>
		<pose>Unspecified</pose>
		<truncated>0</truncated>
		<difficult>0</difficult>
		<bndbox>
			<xmin>1163</xmin>
			<ymin>189</ymin>
			<xmax>1193</xmax>
			<ymax>222</ymax>
		</bndbox>
	</object>
	<object>
		<name>person</name>
		<pose>Unspecified</pose>
		<truncated>0</truncated>
		<difficult>0</difficult>
		<bndbox>
			<xmin>1093</xmin>
			<ymin>140</ymin>
			<xmax>1117</xmax>
			<ymax>171</ymax>
		</bndbox>
	</object>
	<object>
		<name>person</name>
		<pose>Unspecified</pose>
		<truncated>0</truncated>
		<difficult>0</difficult>
		<bndbox>
			<xmin>1115</xmin>
			<ymin>120</ymin>
			<xmax>1133</xmax>
			<ymax>142</ymax>
		</bndbox>
	</object>
	<object>
		<name>person</name>
		<pose>Unspecified</pose>
		<truncated>0</truncated>
		<difficult>0</difficult>
		<bndbox>
			<xmin>1119</xmin>
			<ymin>101</ymin>
			<xmax>1139</xmax>
			<ymax>125</ymax>
		</bndbox>
	</object>
	<object>
		<name>person</name>
		<pose>Unspecified</pose>
		<truncated>0</truncated>
		<difficult>0</difficult>
		<bndbox>
			<xmin>1137</xmin>
			<ymin>84</ymin>
			<xmax>1154</xmax>
			<ymax>110</ymax>
		</bndbox>
	</object>
	<object>
		<name>person</name>
		<pose>Unspecified</pose>
		<truncated>0</truncated>
		<difficult>0</difficult>
		<bndbox>
			<xmin>1167</xmin>
			<ymin>96</ymin>
			<xmax>1183</xmax>
			<ymax>117</ymax>
		</bndbox>
	</object>
	<object>
		<name>person</name>
		<pose>Unspecified</pose>
		<truncated>0</truncated>
		<difficult>0</difficult>
		<bndbox>
			<xmin>1048</xmin>
			<ymin>120</ymin>
			<xmax>1068</xmax>
			<ymax>148</ymax>
		</bndbox>
	</object>
	<object>
		<name>person</name>
		<pose>Unspecified</pose>
		<truncated>0</truncated>
		<difficult>0</difficult>
		<bndbox>
			<xmin>1066</xmin>
			<ymin>104</ymin>
			<xmax>1086</xmax>
			<ymax>126</ymax>
		</bndbox>
	</object>
	<object>
		<name>person</name>
		<pose>Unspecified</pose>
		<truncated>0</truncated>
		<difficult>0</difficult>
		<bndbox>
			<xmin>1071</xmin>
			<ymin>84</ymin>
			<xmax>1088</xmax>
			<ymax>106</ymax>
		</bndbox>
	</object>
	<object>
		<name>person</name>
		<pose>Unspecified</pose>
		<truncated>0</truncated>
		<difficult>0</difficult>
		<bndbox>
			<xmin>950</xmin>
			<ymin>88</ymin>
			<xmax>970</xmax>
			<ymax>117</ymax>
		</bndbox>
	</object>
	<object>
		<name>person</name>
		<pose>Unspecified</pose>
		<truncated>0</truncated>
		<difficult>0</difficult>
		<bndbox>
			<xmin>975</xmin>
			<ymin>98</ymin>
			<xmax>995</xmax>
			<ymax>123</ymax>
		</bndbox>
	</object>
	<object>
		<name>person</name>
		<pose>Unspecified</pose>
		<truncated>0</truncated>
		<difficult>0</difficult>
		<bndbox>
			<xmin>975</xmin>
			<ymin>73</ymin>
			<xmax>993</xmax>
			<ymax>96</ymax>
		</bndbox>
	</object>
	<object>
		<name>person</name>
		<pose>Unspecified</pose>
		<truncated>0</truncated>
		<difficult>0</difficult>
		<bndbox>
			<xmin>1000</xmin>
			<ymin>67</ymin>
			<xmax>1019</xmax>
			<ymax>91</ymax>
		</bndbox>
	</object>
	<object>
		<name>person</name>
		<pose>Unspecified</pose>
		<truncated>0</truncated>
		<difficult>0</difficult>
		<bndbox>
			<xmin>1013</xmin>
			<ymin>92</ymin>
			<xmax>1029</xmax>
			<ymax>116</ymax>
		</bndbox>
	</object>
	<object>
		<name>person</name>
		<pose>Unspecified</pose>
		<truncated>0</truncated>
		<difficult>0</difficult>
		<bndbox>
			<xmin>1005</xmin>
			<ymin>111</ymin>
			<xmax>1022</xmax>
			<ymax>135</ymax>
		</bndbox>
	</object>
	<object>
		<name>person</name>
		<pose>Unspecified</pose>
		<truncated>0</truncated>
		<difficult>0</difficult>
		<bndbox>
			<xmin>1029</xmin>
			<ymin>75</ymin>
			<xmax>1043</xmax>
			<ymax>99</ymax>
		</bndbox>
	</object>
	<object>
		<name>person</name>
		<pose>Unspecified</pose>
		<truncated>0</truncated>
		<difficult>0</difficult>
		<bndbox>
			<xmin>1046</xmin>
			<ymin>80</ymin>
			<xmax>1063</xmax>
			<ymax>101</ymax>
		</bndbox>
	</object>
	<object>
		<name>person</name>
		<pose>Unspecified</pose>
		<truncated>0</truncated>
		<difficult>0</difficult>
		<bndbox>
			<xmin>1089</xmin>
			<ymin>88</ymin>
			<xmax>1104</xmax>
			<ymax>108</ymax>
		</bndbox>
	</object>
</annotation>