<?xml version='1.0' encoding='us-ascii'?>
<annotation>
	<folder>Img_2000</folder>
	<filename>PartB_01140.jpg</filename>
	<path>C:\Users\Administrator\Desktop\dataset_2.0\Img_2000\Img_235.jpeg</path>
	<source>
		<database>Unknown</database>
	</source>
	<size>
		<width>6598</width>
		<height>3072</height>
		<depth>3</depth>
	</size>
	<segmented>0</segmented>
	<object>
		<name>person</name>
		<pose>Unspecified</pose>
		<truncated>0</truncated>
		<difficult>0</difficult>
		<bndbox>
			<xmin>2269</xmin>
			<ymin>1135</ymin>
			<xmax>2573</xmax>
			<ymax>1508</ymax>
		</bndbox>
	</object>
	<object>
		<name>person</name>
		<pose>Unspecified</pose>
		<truncated>0</truncated>
		<difficult>0</difficult>
		<bndbox>
			<xmin>2137</xmin>
			<ymin>944</ymin>
			<xmax>2378</xmax>
			<ymax>1194</ymax>
		</bndbox>
	</object>
	<object>
		<name>person</name>
		<pose>Unspecified</pose>
		<truncated>0</truncated>
		<difficult>0</difficult>
		<bndbox>
			<xmin>2369</xmin>
			<ymin>1004</ymin>
			<xmax>2510</xmax>
			<ymax>1167</ymax>
		</bndbox>
	</object>
	<object>
		<name>person</name>
		<pose>Unspecified</pose>
		<truncated>0</truncated>
		<difficult>0</difficult>
		<bndbox>
			<xmin>2514</xmin>
			<ymin>976</ymin>
			<xmax>2623</xmax>
			<ymax>1099</ymax>
		</bndbox>
	</object>
	<object>
		<name>person</name>
		<pose>Unspecified</pose>
		<truncated>0</truncated>
		<difficult>0</difficult>
		<bndbox>
			<xmin>3033</xmin>
			<ymin>940</ymin>
			<xmax>3164</xmax>
			<ymax>1072</ymax>
		</bndbox>
	</object>
	<object>
		<name>person</name>
		<pose>Unspecified</pose>
		<truncated>0</truncated>
		<difficult>0</difficult>
		<bndbox>
			<xmin>3410</xmin>
			<ymin>976</ymin>
			<xmax>3564</xmax>
			<ymax>1126</ymax>
		</bndbox>
	</object>
	<object>
		<name>person</name>
		<pose>Unspecified</pose>
		<truncated>0</truncated>
		<difficult>0</difficult>
		<bndbox>
			<xmin>3619</xmin>
			<ymin>976</ymin>
			<xmax>3764</xmax>
			<ymax>1158</ymax>
		</bndbox>
	</object>
	<object>
		<name>person</name>
		<pose>Unspecified</pose>
		<truncated>0</truncated>
		<difficult>0</difficult>
		<bndbox>
			<xmin>3719</xmin>
			<ymin>994</ymin>
			<xmax>3851</xmax>
			<ymax>1167</ymax>
		</bndbox>
	</object>
	<object>
		<name>person</name>
		<pose>Unspecified</pose>
		<truncated>0</truncated>
		<difficult>0</difficult>
		<bndbox>
			<xmin>3978</xmin>
			<ymin>1022</ymin>
			<xmax>4146</xmax>
			<ymax>1199</ymax>
		</bndbox>
	</object>
	<object>
		<name>person</name>
		<pose>Unspecified</pose>
		<truncated>0</truncated>
		<difficult>0</difficult>
		<bndbox>
			<xmin>4073</xmin>
			<ymin>1099</ymin>
			<xmax>4228</xmax>
			<ymax>1290</ymax>
		</bndbox>
	</object>
	<object>
		<name>person</name>
		<pose>Unspecified</pose>
		<truncated>0</truncated>
		<difficult>0</difficult>
		<bndbox>
			<xmin>4187</xmin>
			<ymin>1035</ymin>
			<xmax>4355</xmax>
			<ymax>1244</ymax>
		</bndbox>
	</object>
	<object>
		<name>person</name>
		<pose>Unspecified</pose>
		<truncated>0</truncated>
		<difficult>0</difficult>
		<bndbox>
			<xmin>4583</xmin>
			<ymin>1149</ymin>
			<xmax>5028</xmax>
			<ymax>1622</ymax>
		</bndbox>
	</object>
	<object>
		<name>person</name>
		<pose>Unspecified</pose>
		<truncated>0</truncated>
		<difficult>0</difficult>
		<bndbox>
			<xmin>4810</xmin>
			<ymin>1081</ymin>
			<xmax>5114</xmax>
			<ymax>1390</ymax>
		</bndbox>
	</object>
</annotation>