<?xml version='1.0' encoding='us-ascii'?>
<annotation>
	<folder>Img_2000</folder>
	<filename>PartB_00042.jpg</filename>
	<path>C:\Users\Administrator\Desktop\dataset_2.0\Img_2000\Img_042.jpeg</path>
	<source>
		<database>Unknown</database>
	</source>
	<size>
		<width>3000</width>
		<height>2000</height>
		<depth>3</depth>
	</size>
	<segmented>0</segmented>
	<object>
		<name>person</name>
		<pose>Unspecified</pose>
		<truncated>0</truncated>
		<difficult>0</difficult>
		<bndbox>
			<xmin>1134</xmin>
			<ymin>1133</ymin>
			<xmax>1303</xmax>
			<ymax>1342</ymax>
		</bndbox>
	</object>
	<object>
		<name>person</name>
		<pose>Unspecified</pose>
		<truncated>0</truncated>
		<difficult>0</difficult>
		<bndbox>
			<xmin>782</xmin>
			<ymin>1146</ymin>
			<xmax>907</xmax>
			<ymax>1298</ymax>
		</bndbox>
	</object>
	<object>
		<name>person</name>
		<pose>Unspecified</pose>
		<truncated>0</truncated>
		<difficult>0</difficult>
		<bndbox>
			<xmin>103</xmin>
			<ymin>1190</ymin>
			<xmax>311</xmax>
			<ymax>1496</ymax>
		</bndbox>
	</object>
	<object>
		<name>person</name>
		<pose>Unspecified</pose>
		<truncated>0</truncated>
		<difficult>0</difficult>
		<bndbox>
			<xmin>351</xmin>
			<ymin>1225</ymin>
			<xmax>486</xmax>
			<ymax>1373</ymax>
		</bndbox>
	</object>
	<object>
		<name>person</name>
		<pose>Unspecified</pose>
		<truncated>0</truncated>
		<difficult>0</difficult>
		<bndbox>
			<xmin>245</xmin>
			<ymin>1133</ymin>
			<xmax>345</xmax>
			<ymax>1254</ymax>
		</bndbox>
	</object>
	<object>
		<name>person</name>
		<pose>Unspecified</pose>
		<truncated>0</truncated>
		<difficult>0</difficult>
		<bndbox>
			<xmin>143</xmin>
			<ymin>1065</ymin>
			<xmax>228</xmax>
			<ymax>1160</ymax>
		</bndbox>
	</object>
	<object>
		<name>person</name>
		<pose>Unspecified</pose>
		<truncated>0</truncated>
		<difficult>0</difficult>
		<bndbox>
			<xmin>45</xmin>
			<ymin>1027</ymin>
			<xmax>120</xmax>
			<ymax>1117</ymax>
		</bndbox>
	</object>
	<object>
		<name>person</name>
		<pose>Unspecified</pose>
		<truncated>0</truncated>
		<difficult>0</difficult>
		<bndbox>
			<xmin>288</xmin>
			<ymin>1029</ymin>
			<xmax>351</xmax>
			<ymax>1104</ymax>
		</bndbox>
	</object>
	<object>
		<name>person</name>
		<pose>Unspecified</pose>
		<truncated>0</truncated>
		<difficult>0</difficult>
		<bndbox>
			<xmin>443</xmin>
			<ymin>1025</ymin>
			<xmax>522</xmax>
			<ymax>1098</ymax>
		</bndbox>
	</object>
	<object>
		<name>person</name>
		<pose>Unspecified</pose>
		<truncated>0</truncated>
		<difficult>0</difficult>
		<bndbox>
			<xmin>538</xmin>
			<ymin>998</ymin>
			<xmax>622</xmax>
			<ymax>1094</ymax>
		</bndbox>
	</object>
	<object>
		<name>person</name>
		<pose>Unspecified</pose>
		<truncated>0</truncated>
		<difficult>0</difficult>
		<bndbox>
			<xmin>634</xmin>
			<ymin>994</ymin>
			<xmax>695</xmax>
			<ymax>1060</ymax>
		</bndbox>
	</object>
	<object>
		<name>person</name>
		<pose>Unspecified</pose>
		<truncated>0</truncated>
		<difficult>0</difficult>
		<bndbox>
			<xmin>757</xmin>
			<ymin>1023</ymin>
			<xmax>824</xmax>
			<ymax>1106</ymax>
		</bndbox>
	</object>
	<object>
		<name>person</name>
		<pose>Unspecified</pose>
		<truncated>0</truncated>
		<difficult>0</difficult>
		<bndbox>
			<xmin>809</xmin>
			<ymin>981</ymin>
			<xmax>868</xmax>
			<ymax>1050</ymax>
		</bndbox>
	</object>
	<object>
		<name>person</name>
		<pose>Unspecified</pose>
		<truncated>0</truncated>
		<difficult>0</difficult>
		<bndbox>
			<xmin>895</xmin>
			<ymin>1002</ymin>
			<xmax>966</xmax>
			<ymax>1075</ymax>
		</bndbox>
	</object>
	<object>
		<name>person</name>
		<pose>Unspecified</pose>
		<truncated>0</truncated>
		<difficult>0</difficult>
		<bndbox>
			<xmin>1084</xmin>
			<ymin>958</ymin>
			<xmax>1147</xmax>
			<ymax>1033</ymax>
		</bndbox>
	</object>
	<object>
		<name>person</name>
		<pose>Unspecified</pose>
		<truncated>0</truncated>
		<difficult>0</difficult>
		<bndbox>
			<xmin>1234</xmin>
			<ymin>981</ymin>
			<xmax>1288</xmax>
			<ymax>1056</ymax>
		</bndbox>
	</object>
	<object>
		<name>person</name>
		<pose>Unspecified</pose>
		<truncated>0</truncated>
		<difficult>0</difficult>
		<bndbox>
			<xmin>1376</xmin>
			<ymin>994</ymin>
			<xmax>1445</xmax>
			<ymax>1065</ymax>
		</bndbox>
	</object>
	<object>
		<name>person</name>
		<pose>Unspecified</pose>
		<truncated>0</truncated>
		<difficult>0</difficult>
		<bndbox>
			<xmin>1474</xmin>
			<ymin>1000</ymin>
			<xmax>1541</xmax>
			<ymax>1077</ymax>
		</bndbox>
	</object>
	<object>
		<name>person</name>
		<pose>Unspecified</pose>
		<truncated>0</truncated>
		<difficult>0</difficult>
		<bndbox>
			<xmin>1511</xmin>
			<ymin>998</ymin>
			<xmax>1566</xmax>
			<ymax>1060</ymax>
		</bndbox>
	</object>
	<object>
		<name>person</name>
		<pose>Unspecified</pose>
		<truncated>0</truncated>
		<difficult>0</difficult>
		<bndbox>
			<xmin>1603</xmin>
			<ymin>1015</ymin>
			<xmax>1657</xmax>
			<ymax>1077</ymax>
		</bndbox>
	</object>
	<object>
		<name>person</name>
		<pose>Unspecified</pose>
		<truncated>0</truncated>
		<difficult>0</difficult>
		<bndbox>
			<xmin>1651</xmin>
			<ymin>960</ymin>
			<xmax>1705</xmax>
			<ymax>1023</ymax>
		</bndbox>
	</object>
	<object>
		<name>person</name>
		<pose>Unspecified</pose>
		<truncated>0</truncated>
		<difficult>0</difficult>
		<bndbox>
			<xmin>1718</xmin>
			<ymin>987</ymin>
			<xmax>1761</xmax>
			<ymax>1044</ymax>
		</bndbox>
	</object>
	<object>
		<name>person</name>
		<pose>Unspecified</pose>
		<truncated>0</truncated>
		<difficult>0</difficult>
		<bndbox>
			<xmin>1776</xmin>
			<ymin>1027</ymin>
			<xmax>1841</xmax>
			<ymax>1098</ymax>
		</bndbox>
	</object>
	<object>
		<name>person</name>
		<pose>Unspecified</pose>
		<truncated>0</truncated>
		<difficult>0</difficult>
		<bndbox>
			<xmin>1797</xmin>
			<ymin>990</ymin>
			<xmax>1853</xmax>
			<ymax>1046</ymax>
		</bndbox>
	</object>
	<object>
		<name>person</name>
		<pose>Unspecified</pose>
		<truncated>0</truncated>
		<difficult>0</difficult>
		<bndbox>
			<xmin>1899</xmin>
			<ymin>1021</ymin>
			<xmax>1955</xmax>
			<ymax>1100</ymax>
		</bndbox>
	</object>
	<object>
		<name>person</name>
		<pose>Unspecified</pose>
		<truncated>0</truncated>
		<difficult>0</difficult>
		<bndbox>
			<xmin>2028</xmin>
			<ymin>1025</ymin>
			<xmax>2086</xmax>
			<ymax>1104</ymax>
		</bndbox>
	</object>
	<object>
		<name>person</name>
		<pose>Unspecified</pose>
		<truncated>0</truncated>
		<difficult>0</difficult>
		<bndbox>
			<xmin>2155</xmin>
			<ymin>1023</ymin>
			<xmax>2203</xmax>
			<ymax>1096</ymax>
		</bndbox>
	</object>
	<object>
		<name>person</name>
		<pose>Unspecified</pose>
		<truncated>0</truncated>
		<difficult>0</difficult>
		<bndbox>
			<xmin>2232</xmin>
			<ymin>1006</ymin>
			<xmax>2303</xmax>
			<ymax>1094</ymax>
		</bndbox>
	</object>
	<object>
		<name>person</name>
		<pose>Unspecified</pose>
		<truncated>0</truncated>
		<difficult>0</difficult>
		<bndbox>
			<xmin>2324</xmin>
			<ymin>1006</ymin>
			<xmax>2388</xmax>
			<ymax>1096</ymax>
		</bndbox>
	</object>
	<object>
		<name>person</name>
		<pose>Unspecified</pose>
		<truncated>0</truncated>
		<difficult>0</difficult>
		<bndbox>
			<xmin>2626</xmin>
			<ymin>1035</ymin>
			<xmax>2703</xmax>
			<ymax>1152</ymax>
		</bndbox>
	</object>
	<object>
		<name>person</name>
		<pose>Unspecified</pose>
		<truncated>0</truncated>
		<difficult>0</difficult>
		<bndbox>
			<xmin>2705</xmin>
			<ymin>1035</ymin>
			<xmax>2776</xmax>
			<ymax>1144</ymax>
		</bndbox>
	</object>
</annotation>