<?xml version='1.0' encoding='us-ascii'?>
<annotation>
	<folder>750-999</folder>
	<filename>PartA_00776.jpg</filename>
	<path>/media/zrcai/study/lab/0818data/750-999/750-999/776.jpg</path>
	<source>
		<database>Unknown</database>
	</source>
	<size>
		<width>1266</width>
		<height>723</height>
		<depth>3</depth>
	</size>
	<segmented>0</segmented>
	<object>
    <name>person</name>
		<pose>Unspecified</pose>
		<truncated>0</truncated>
		<difficult>0</difficult>
		<bndbox>
			<xmin>1004</xmin>
			<ymin>258</ymin>
			<xmax>1043</xmax>
			<ymax>315</ymax>
		</bndbox>
	</object>
	<object>
    <name>person</name>
		<pose>Unspecified</pose>
		<truncated>0</truncated>
		<difficult>0</difficult>
		<bndbox>
			<xmin>604</xmin>
			<ymin>102</ymin>
			<xmax>621</xmax>
			<ymax>127</ymax>
		</bndbox>
	</object>
	<object>
    <name>person</name>
		<pose>Unspecified</pose>
		<truncated>0</truncated>
		<difficult>0</difficult>
		<bndbox>
			<xmin>1091</xmin>
			<ymin>94</ymin>
			<xmax>1110</xmax>
			<ymax>112</ymax>
		</bndbox>
	</object>
	<object>
    <name>person</name>
		<pose>Unspecified</pose>
		<truncated>0</truncated>
		<difficult>0</difficult>
		<bndbox>
			<xmin>1125</xmin>
			<ymin>93</ymin>
			<xmax>1148</xmax>
			<ymax>114</ymax>
		</bndbox>
	</object>
</annotation>